okf/__init__.py
okf/model.py
okf/optimizer.py
okf/utils.py
okf/example/__init__.py
okf/example/simple_lidar_model.py
okf/example/simple_lidar_simulator.py
Optimized_Kalman_Filter-0.0.9.dist-info/LICENSE.txt
Optimized_Kalman_Filter-0.0.9.dist-info/METADATA
Optimized_Kalman_Filter-0.0.9.dist-info/WHEEL
Optimized_Kalman_Filter-0.0.9.dist-info/top_level.txt
Optimized_Kalman_Filter-0.0.9.dist-info/RECORD
