Metadata-Version: 2.1
Name: Optimized-Kalman-Filter
Version: 0.0.9
Summary: Optimization of a Kalman Filter from data of states and their observations.
Home-page: https://github.com/ido90/Optimized-Kalman-Filter
Author: Ido Greenberg
License: MIT
Keywords: OKF,Optimized Kalman Filter,Kalman Filter
Platform: UNKNOWN
Classifier: License :: OSI Approved :: MIT License
Classifier: Programming Language :: Python :: 3
Requires-Python: >=3.5
License-File: LICENSE.txt
Requires-Dist: torch
